raindrops/__init__.py
raindrops/cli.py
raindrops/templates/cloud_function_firestore.template
raindrops/templates/cloud_function_gcs.template
raindrops/templates/cloud_function_http.template
raindrops/templates/cloud_function_pubsub.template
raindrops/templates/cloudbuild_yaml.template
raindrops/templates/env_yaml.template
raindrops/templates/gcloudignore.template
raindrops/templates/requirements.template
raindrops-0.0.3.dist-info/LICENSE
raindrops-0.0.3.dist-info/METADATA
raindrops-0.0.3.dist-info/WHEEL
raindrops-0.0.3.dist-info/entry_points.txt
raindrops-0.0.3.dist-info/top_level.txt
raindrops-0.0.3.dist-info/RECORD
